astra_multivector/__init__.py
astra_multivector/astra_multi_vector_table.py
astra_multivector/async_astra_multi_vector_table.py
astra_multivector/vector_column_options.py
astra_multivector/late_interaction/README.md
astra_multivector/late_interaction/__init__.py
astra_multivector/late_interaction/late_interaction_pipeline.py
astra_multivector/late_interaction/utils.py
astra_multivector/late_interaction/models/__init__.py
astra_multivector/late_interaction/models/base.py
astra_multivector/late_interaction/models/colpali.py
astra_multivector-0.2.0.dist-info/METADATA
astra_multivector-0.2.0.dist-info/WHEEL
astra_multivector-0.2.0.dist-info/licenses/LICENSE
astra_multivector-0.2.0.dist-info/RECORD
