Metadata-Version: 2.4
Name: astra-multivector
Version: 0.2.0
Summary: Multivector Tables using the DataAPI from AstraDB
Author-email: Brian O'Grady <brian.ogrady@datastax.com>
Maintainer-email: Brian O'Grady <brian.ogrady@datastax.com>
License:                                  Apache License
License-File: LICENSE
Keywords: astradb,colbert,database,embeddings,late-interaction,similarity-search,vector
Classifier: Development Status :: 4 - Beta
Classifier: Intended Audience :: Developers
Classifier: License :: OSI Approved :: Apache Software License
Classifier: Programming Language :: Python :: 3
Classifier: Programming Language :: Python :: 3.12
Classifier: Topic :: Database
Classifier: Topic :: Scientific/Engineering :: Artificial Intelligence
Classifier: Topic :: Software Development :: Libraries
Requires-Python: >=3.12
Requires-Dist: astrapy==2.0.1
Requires-Dist: pydantic>=2.10.6
Requires-Dist: python-dotenv>=1.0.1
Requires-Dist: rerankers[api,transformers]>=0.8.0
Requires-Dist: sentence-transformers>=3.4.1
Requires-Dist: tqdm>=4.67.1
Requires-Dist: transformers>=4.38.2
Provides-Extra: all
Requires-Dist: async-lru>=2.0.5; extra == 'all'
Requires-Dist: colpali-engine<0.4.0,>=0.3.1; extra == 'all'
Requires-Dist: ipywidgets>=8.0.0; extra == 'all'
Requires-Dist: jupyter>=1.0.0; extra == 'all'
Requires-Dist: matplotlib>=3.7.0; extra == 'all'
Requires-Dist: notebook>=7.0.0; extra == 'all'
Requires-Dist: numpy>=1.24.0; extra == 'all'
Requires-Dist: pandas>=2.0.0; extra == 'all'
Requires-Dist: pdf2image>=1.16.3; extra == 'all'
Requires-Dist: pillow>=10.0.0; extra == 'all'
Requires-Dist: scikit-learn>=1.3.0; extra == 'all'
Requires-Dist: scipy>=1.15.2; extra == 'all'
Requires-Dist: torch>=2.2.0; extra == 'all'
Requires-Dist: weasyprint>=60.0; extra == 'all'
Provides-Extra: dev
Requires-Dist: build>=1.0.3; extra == 'dev'
Requires-Dist: mypy>=1.11.0; extra == 'dev'
Requires-Dist: pre-commit>=3.7.0; extra == 'dev'
Requires-Dist: pytest-asyncio>=0.23.0; extra == 'dev'
Requires-Dist: pytest-cov>=5.0.0; extra == 'dev'
Requires-Dist: pytest-mock>=3.14.0; extra == 'dev'
Requires-Dist: pytest-xdist>=3.6.0; extra == 'dev'
Requires-Dist: pytest>=8.2.0; extra == 'dev'
Requires-Dist: ruff<0.10,>=0.9.7; extra == 'dev'
Requires-Dist: twine>=4.0.2; extra == 'dev'
Requires-Dist: types-pillow>=10.2.0.20240213; extra == 'dev'
Requires-Dist: types-requests>=2.32.0; extra == 'dev'
Provides-Extra: late-interaction
Requires-Dist: async-lru>=2.0.5; extra == 'late-interaction'
Requires-Dist: colpali-engine<0.4.0,>=0.3.1; extra == 'late-interaction'
Requires-Dist: numpy>=1.24.0; extra == 'late-interaction'
Requires-Dist: scikit-learn>=1.3.0; extra == 'late-interaction'
Requires-Dist: scipy>=1.15.2; extra == 'late-interaction'
Requires-Dist: torch>=2.2.0; extra == 'late-interaction'
Provides-Extra: notebooks
Requires-Dist: ipywidgets>=8.0.0; extra == 'notebooks'
Requires-Dist: jupyter>=1.0.0; extra == 'notebooks'
Requires-Dist: matplotlib>=3.7.0; extra == 'notebooks'
Requires-Dist: notebook>=7.0.0; extra == 'notebooks'
Requires-Dist: pandas>=2.0.0; extra == 'notebooks'
Requires-Dist: pdf2image>=1.16.3; extra == 'notebooks'
Requires-Dist: pillow>=10.0.0; extra == 'notebooks'
Requires-Dist: weasyprint>=60.0; extra == 'notebooks'
Provides-Extra: test
Requires-Dist: build>=1.0.3; extra == 'test'
Requires-Dist: mypy>=1.11.0; extra == 'test'
Requires-Dist: pre-commit>=3.7.0; extra == 'test'
Requires-Dist: pytest-asyncio>=0.23.0; extra == 'test'
Requires-Dist: pytest-cov>=5.0.0; extra == 'test'
Requires-Dist: pytest-mock>=3.14.0; extra == 'test'
Requires-Dist: pytest-xdist>=3.6.0; extra == 'test'
Requires-Dist: pytest>=8.2.0; extra == 'test'
Requires-Dist: ruff<0.10,>=0.9.7; extra == 'test'
Requires-Dist: twine>=4.0.2; extra == 'test'
Requires-Dist: types-pillow>=10.2.0.20240213; extra == 'test'
Requires-Dist: types-requests>=2.32.0; extra == 'test'
